md2htmlify/__init__.py
md2htmlify/cli.py
md2htmlify/md_to_html.py
md2htmlify/libs/custom_css.css
md2htmlify/libs/tailwind.min.css
md2htmlify/libs/tex-mml-chtml.js
md2htmlify-0.0.1.dist-info/LICENSE
md2htmlify-0.0.1.dist-info/METADATA
md2htmlify-0.0.1.dist-info/WHEEL
md2htmlify-0.0.1.dist-info/entry_points.txt
md2htmlify-0.0.1.dist-info/top_level.txt
md2htmlify-0.0.1.dist-info/RECORD
