Metadata-Version: 2.1
Name: md2htmlify
Version: 0.0.1
Summary: A simple, user-friendly library for converting Markdown files to HTML, with optional local or CDN-based math and styling dependencies.
Home-page: https://github.com/codeperfectplus/md2htmlify
Author: Deepak Raj
Author-email: deepak008@live.com
License: MIT
Project-URL: Documentation, https://md2htmlify.readthedocs.io/en/latest/
Project-URL: Source, https://github.com/codeperfectplus/md2htmlify
Project-URL: Tracker, https://github.com/codeperfectplus/md2htmlify/issues
Keywords: markdown,html,converter,mathjax,tailwind,latex,documentation
Classifier: Development Status :: 5 - Production/Stable
Classifier: Programming Language :: Python :: 3
Classifier: License :: OSI Approved :: MIT License
Classifier: Operating System :: OS Independent
Classifier: Intended Audience :: Developers
Requires-Python: >=3.6
License-File: LICENSE
Requires-Dist: beautifulsoup4==4.13.4
Requires-Dist: markdown==3.8
Requires-Dist: playwright==1.51.0
Requires-Dist: asyncio==3.4.3
Requires-Dist: aiofiles==24.1.0
